README.md
setup.py
netbox_negistry_importer/__init__.py
netbox_negistry_importer/cli.py
netbox_negistry_importer/config.py
netbox_negistry_importer.egg-info/PKG-INFO
netbox_negistry_importer.egg-info/SOURCES.txt
netbox_negistry_importer.egg-info/dependency_links.txt
netbox_negistry_importer.egg-info/entry_points.txt
netbox_negistry_importer.egg-info/requires.txt
netbox_negistry_importer.egg-info/top_level.txt
netbox_negistry_importer/importers/Negistry.py
netbox_negistry_importer/importers/__init__.py
tests/__init__.py
tests/test_netbox_negistry_importer.py