Metadata-Version: 2.1
Name: netbox-negistry-importer
Version: 0.2.0
Summary: Imports ripe IP ranges from Negistry into Netbox
Home-page: https://gitlab.cesnet.cz/701/done/netbox_negistry_importer
Author: Jan Krupa
Author-email: jan.krupa@cesnet.cz
License: UNKNOWN
Project-URL: Homepage, https://gitlab.cesnet.cz/701/done/netbox_negistry_importer
Project-URL: Repository, https://gitlab.cesnet.cz/701/done/netbox_negistry_importer
Platform: UNKNOWN
Classifier: Programming Language :: Python :: 3.8
Classifier: License :: OSI Approved :: MIT License
Classifier: Operating System :: OS Independent
Requires-Python: >=3.8
Provides-Extra: dev
